Metadata-Version: 1.0
Name: maginner
Version: 0.1
Summary: Create banners easily
Home-page: UNKNOWN
Author: germfreekai
Author-email: UNKNOWN
License: UNKNOWN
Platform: UNKNOWN
